{
  "": {
    "492AC53C4CD783EAA86153AB38D80222": "令玩家及载具加速并注入氮气的火焰圈。",
    "A5628F3A4DC5D492E2DA7E9CF930BF18": "令玩家及载具加速并注入氮气的火焰圈。",
    "B9DA59194217C6157F51BF91F4AB6F06": "令玩家及载具加速并注入氮气的火焰圈。",
    "5351992C4B32C7F25D82528A669548C2": "默认",
    "549E3012422D07A3D78F799836875310": "False",
    "AD57B7D341405AC4429DB896D4DEEEB0": "False",
    "F58EB5CC4C22B324F61F359D18B054B3": "半程",
    "13CCF103419262C02BB551905B56F118": "手动结束",
    "B81E71814972C6C9CDA98AB6F5C84418": "氮气圈",
    "EC1432CF49CE5101074E5F8C4E41D270": "氮气圈",
    "7F68D968423064E2ED78CC88C8D6421A": "无",
    "F77398464268F4AF58F846A5F812E2D5": "无",
    "1D8E0CA94EC91AA4E96E4E94EEE639CD": "True",
    "F06C553B40C0650DDC09EAAE3776FD0A": "True",
    "E6809D7B4C69C6150EAB5990844016DD": "{0} 米/秒",
    "CC82B2CA49FB779B5CDC60AEDD15C2B3": "{0}x",
    "BD8F0C8F45892217242BD3A7AD76C322": "{0} {1}|plural(one=秒, other=秒)",
    "FB4B6CCD4F6CDBD0EBFA208A726606FD": "{0}秒"
  },
  "Fort.Actor.Building.Defaults": {
    "OptionDefinitionContainer.LabelOverride": "标签"
  },
  "UserOptionDefinition": {
    "Device_NitroHoop_C.Add Columns.DisplayName": "添加柱体",
    "Device_NitroHoop_C.bAddStand.DisplayName": "添加支撑",
    "Device_NitroHoop_C.bAddStand.Description": "在每个底部添加短小支撑。",
    "Device_NitroHoop_C.Add Columns.Description": "添加柱体堆叠，支撑圈。",
    "Device_NitroHoop_C.AddedPlayerVelocity.DisplayName": "添加玩家速度",
    "Device_NitroHoop_C.CooldownDelay.Description": "触发冷却后、进入冷却阶段前需要等待的时间（以秒计）。不适用于“开始冷却”或“禁用”触发的冷却。",
    "Device_NitroHoop_C.AllowCooldown.DisplayName": "允许冷却",
    "Device_NitroHoop_C.AllowCooldown.Description": "允许设备在被玩家或载具触发后进入冷却状态。",
    "EEnabledOnPhase.Always.DisplayName": "永远",
    "Device_NitroHoop_C.BaseType.DisplayName": "基础类型",
    "Device_NitroHoop_C.CooldownDelay.DisplayName": "冷却延迟",
    "Device_NitroHoop_C.CooldownDuration.DisplayName": "冷却时长",
    "Device_NitroHoop_C.bCooldownAtGameStart.DisplayName": "游戏开始时冷却",
    "Device_NitroHoop_C.bCooldownAtRoundStart.DisplayName": "回合开始时冷却",
    "EEnabledOnPhase.Create Only.DisplayName": "仅限创建",
    "HoopOption_BaseType.Default.DisplayName": "默认",
    "Device_NitroHoop_C.CooldownDuration.Description": "确定冷却状态持续时间（以秒为单位）。手动结束——冷却状态不会自己结束，设备必须通过启用、禁用冷却或在阶段启用重新启用。",
    "Device_NitroHoop_C.AddedPlayerVelocity.Description": "确定选项启用时，玩家通过圈时的额外速度（以 m/s 为单位)。",
    "Device_NitroHoop_C.EnableOnPhase.Description": "确定开始启动设备的游戏阶段。游戏前阶段包括游戏开始前的所有阶段（玩家等待大厅和游戏开始倒计时）。",
    "Device_NitroHoop_C.VehicleVelocityMultiplier.Description": "确定启用时，应用于载具通过圈的速度加成。",
    "Device_NitroHoop_C.BaseType.Description": "确定圈的基底。半程——用于一半进入地面的圈。",
    "Device_NitroHoop_C.bEnableCooldown.Description": "确定冷却是否默认启用。冷却启用后，使用圈时将令其自动进入冷却阶段，禁用设备。 冷却状态结束后，圈将自动重新启用。",
    "Device_NitroHoop_C.bCooldownAtRoundStart.Description": "确定新回合开始时，圈是否进入冷却状态，包括游戏的初始回合。要让选项起效，回合开始时设备必须处于启用状态。",
    "Device_NitroHoop_C.bCooldownAtGameStart.Description": "确定游戏开始时，圈是否进入冷却状态。要让选项起效，游戏开始时设备必须处于启用状态。",
    "Device_NitroHoop_C.Disable.DisplayName": "禁用",
    "Device_NitroHoop_C.Disable.Description": "禁用设备，进入冷却状态，直到启动或阶段启动触发。",
    "Device_NitroHoop_C.DisallowCooldown.DisplayName": "不允许冷却",
    "Device_NitroHoop_C.Enable.DisplayName": "启用",
    "Device_NitroHoop_C.bEnableCooldown.DisplayName": "启用冷却",
    "Device_NitroHoop_C.EnableOnPhase.DisplayName": "在该阶段启用",
    "Device_NitroHoop_C.Enable.Description": "启用设备，结束冷却状态。",
    "Device_NitroHoop_C.StartCooldown.Description": "如可行，进入冷却状态，根据冷却时长重启设备。如设备已经处于冷却状态，重启计时器。",
    "Device_NitroHoop_C.OnTriggeredByPlayer.Description": "一名玩家触发设备时触发。",
    "Device_NitroHoop_C.OnTriggeredByVehicle.Description": "一辆载具触发设备时触发，驾驶员作为发起者。",
    "Device_NitroHoop_C.OnEnabled.Description": "设备在禁用后启用时触发，可能经过冷却阶段。",
    "Device_NitroHoop_C.OnStartCooldown.Description": "设备进入冷却状态时触发，进入禁用阶段。不可通过手动调用禁用触发。",
    "EEnabledOnPhase.Gameplay Only.DisplayName": "仅限游戏",
    "HoopOption_BaseType.Halfway.DisplayName": "半程",
    "EEnabledOnPhase.None.DisplayName": "无",
    "HoopOption_BaseType.None.DisplayName": "无",
    "BoolMetaData.FalseDisplayName": "关",
    "BoolMetaData.TrueDisplayName": "开",
    "Device_NitroHoop_C.OnEnabled.DisplayName": "启用时",
    "Device_NitroHoop_C.OnStartCooldown.DisplayName": "开始冷却时",
    "Device_NitroHoop_C.OnTriggeredByPlayer.DisplayName": "由玩家触发时",
    "Device_NitroHoop_C.OnTriggeredByVehicle.DisplayName": "由载具触发时",
    "EEnabledOnPhase.Pre-Game Only.DisplayName": "仅限游戏倒计时",
    "Device_NitroHoop_C.DisallowCooldown.Description": "阻止设备在使用后进入冷却状态。仅在“允许冷却”触发后，使用设备才会进入冷却状态。如设备当前处于冷却状态，则结束冷却状态并重启设备。",
    "Device_NitroHoop_C.StartCooldown.DisplayName": "开始冷却",
    "Device_NitroHoop_C.VehicleVelocityMultiplier.DisplayName": "载具速度加成"
  }
}