{
  "": {
    "43CCE51A446260A717898CA3E6AD1DA4": "1 ห้อง",
    "A8DB6BDE45A81CBEB458639DD7533B14": "โน้ต 1/16",
    "80B1D52C46C17679A5EF1FBE603099A6": "โน้ต 1/2",
    "93550A5C41257E0C9DC336ACC3F8DA4A": "โน้ต 1/32",
    "1212FF444B7409EB38FA5BBBB0CF2347": "โน้ต 1/4",
    "341301A94589B772E05BC5B62D205D11": "โน้ต 1/64",
    "F54118A746850FE875523EB3F2506F13": "โน้ต 1/8",
    "7C92B03C436FE7D5D56CD1970B4ABDBC": "2 ห้อง",
    "A112EC524CE4ECA57F7BBBB17323D0BA": "4 ห้อง",
    "61B45D3D48BA63DE75B0B5A3EE573FD5": "เพิ่มเอฟเฟกต์เอคโคให้กับสัญญาณที่มาจากตัวสร้างเสียงของ Patchwork ก่อนที่จะส่งไปยังเอาต์พุต เช่น ลำโพง Patchwork",
    "8AA60CAB4DE8E925AFC76E927B197D34": "เพิ่มเอฟเฟกต์เอคโคให้กับสัญญาณที่มาจากตัวสร้างเสียงของ Patchwork ก่อนที่จะส่งไปยังเอาต์พุต เช่น ลำโพง Patchwork",
    "799D6A2A42305ABB4653CBAD0EC70E2E": "Patchwork Audio Effect",
    "09F01F834F96541459C3DDA6AE3B0519": "เอฟเฟกต์เอคโคของ Patchwork",
    "D7EECD8A4AA0FFE46347D9B7E83F7A1B": "เอฟเฟกต์เอคโคของ Patchwork"
  },
  "Fort.Actor.Building.Defaults": {
    "OptionDefinitionContainer.LabelOverride": "ป้าย"
  },
  "UserOptionDefinition": {
    "02DB7A7C46AD84E42A7FA180D2087E91": "อนุญาตให้เข้าถึงผ่านสายเคเบิล",
    "EEnabledOnPhase.Always.DisplayName": "ตลอดเวลา",
    "Device_ModularEchoEffect_C.AudioIn.DisplayName": "เสียงขาเข้า",
    "Device_ModularEchoEffect_C.AudioOut.DisplayName": "เสียงขาออก",
    "Device_ModularEchoEffect_C.BeatIn.DisplayName": "จังหวะขาเข้า",
    "Device_ModularEchoEffect_C.Feedback.Description": "ควบคุมจำนวนการซ้ำที่เกิดขึ้น ค่าสูงขึ้นจะเพิ่มความเข้มข้นและระยะเวลาของเอฟเฟกต์เอคโค",
    "EEnabledOnPhase.Create Only.DisplayName": "เฉพาะสร์าง",
    "Device_ModularEchoEffect_C.Mix.Description": "กำหนดปริมาณเอาต์พุตเสียงที่เอฟเฟกต์นี้จะประมวลผล",
    "Device_ModularEchoEffect_C.AllowPortSelection.Description": "กำหนดว่าเครื่องมือ Patchwork สามารถเข้าถึงพอร์ตอินพุตหรือเอาต์พุตของสายเคเบิลบนอุปกรณ์ได้หรือไม่",
    "Device_ModularEchoEffect_C.EnabledOnPhase.Description": "กำหนดช่วงเวลาในเกมที่จะเปิดใช้งานอุปกรณ์ ช่วงก่อนเริ่มเกมประกอบด้วยระยะต่าง ๆ ทั้งหมดก่อนเริ่มเกม (เช่น ล็อบบี้ก่อนเริ่มเกมหรือการนับถอยหลังก่อนเริ่มเกม) การตั้งค่านี้จะไม่มีผลกับโหมดแก้ไข",
    "Device_ModularEchoEffect_C.Disable.DisplayName": "ปิดใช้งาน",
    "Device_ModularEchoEffect_C.Disable.Description": "ปิดใช้งานอุปกรณ์เมื่อเกิดเหตุการณ์",
    "EFabricNoteStyle.Dotted.DisplayName": "จุด",
    "Device_ModularEchoEffect_C.Enable.DisplayName": "เปิดใช้งาน",
    "Device_ModularEchoEffect_C.EnabledOnPhase.DisplayName": "เปิดใช้งานตามช่วงเวลา",
    "Device_ModularEchoEffect_C.Enable.Description": "เปิดใช้งานอุปกรณ์เมื่อเกิดเหตุการณ์",
    "Device_ModularEchoEffect_C.Feedback.DisplayName": "ฟีดแบ็ก",
    "Device_ModularEchoEffect_C.FeedbackIn.DisplayName": "ฟีดแบ็กขาเข้า",
    "Device_ModularEchoEffect_C.Filter.DisplayName": "ฟิลเตอร์",
    "Device_ModularEchoEffect_C.FilterIn.DisplayName": "ฟิลเตอร์ขาเข้า",
    "Device_ModularEchoEffect_C.Filter.Description": "ฟิลเตอร์ความถี่ของสัญญาณที่ดีเลย์โดยใช้ฟิลเตอร์แบบปล่อยย่านต่ำผ่านทางด้านซ้าย และใช้ฟิลเตอร์แบบปล่อยย่านสูงผ่านทางด้านขวา",
    "EEnabledOnPhase.Gameplay Only.DisplayName": "เกมเพลย์เท่านั้น",
    "Device_ModularEchoEffect_C.LegalInfo.DisplayName": "ข้อมูลทางกฎหมาย",
    "Device_ModularEchoEffect_C.Mix.DisplayName": "มิกซ์",
    "Device_ModularEchoEffect_C.MixIn.DisplayName": "การมิกซ์เสียงขาเข้า",
    "EEnabledOnPhase.None.DisplayName": "ไม่มี",
    "BoolMetaData.FalseDisplayName": "ปิด",
    "BoolMetaData.TrueDisplayName": "เปิด",
    "Device_ModularEchoEffect_C.OnDisabled.DisplayName": "เมื่อปิดใช้งาน",
    "Device_ModularEchoEffect_C.OnEnabled.DisplayName": "เมื่อเปิดใช้งาน",
    "E_Fabric_LegalText.Patchwork.DisplayName": "Patchwork",
    "Device_ModularEchoEffect_C.LegalInfo.Description": "โปรดทราบ: การใช้อุปกรณ์เสียง Patchwork จะจำกัดเฉพาะการสร้างสรรค์ผลงานดนตรีใหม่และเป็นผลงานต้นฉบับเท่านั้น",
    "Device_ModularEchoEffect_C.PowerButtonIn.DisplayName": "ปุ่มเปิด/ปิดขาเข้า",
    "EEnabledOnPhase.Pre-Game Only.DisplayName": "เฉพาะแมตช์ที่รอเริ่ม",
    "Device_ModularEchoEffect_C.Style.Description": "เลือกสไตล์สำหรับจังหวะการซิงค์ที่เลือก \"ตรง\" จะส่งผลลัพธ์ตามจังหวะการซิงค์ที่กำหนดไว้, \"สามพยางค์\" จะส่งผลลัพธ์ในความรู้สึกแบบจังหวะสับเปลี่ยนที่สองในสามของจังหวะการซิงค์ และ \"จุด\" จะส่งผลลัพธ์ในความรู้สึกแบบจังหวะเน้นเบาที่หนึ่งเท่าครึ่งของจังหวะการซิงค์",
    "Device_ModularEchoEffect_C.AudioOut.Description": "เลือกจุดหมายปลายทางให้สายเคเบิลเสียงขาออกของอุปกรณ์นี้",
    "Device_ModularEchoEffect_C.AudioIn.Description": "กำหนดอินพุตสำหรับพอร์ตเสียงขาเข้าของอุปกรณ์นี้",
    "Device_ModularEchoEffect_C.BeatIn.Description": "กำหนดอินพุตให้กับปุ่มหมุนปรับดีเลย์จังหวะของอุปกรณ์นี้",
    "Device_ModularEchoEffect_C.FeedbackIn.Description": "กำหนดอินพุตให้กับปุ่มหมุนปรับฟีดแบ็กของอุปกรณ์นี้",
    "Device_ModularEchoEffect_C.FilterIn.Description": "กำหนดอินพุตให้กับปุ่มหมุนปรับฟิลเตอร์ของอุปกรณ์นี้",
    "Device_ModularEchoEffect_C.MixIn.Description": "กำหนดอินพุตให้กับปุ่มหมุนปรับมิกซ์เสียงของอุปกรณ์นี้",
    "Device_ModularEchoEffect_C.StyleIn.Description": "กำหนดอินพุตให้กับเมนูแบบหมุนสำหรับสไตล์ของอุปกรณ์นี้",
    "Device_ModularEchoEffect_C.BeatDelay.Description": "กำหนดเวลาที่จะได้ยินเสียงเอคโคหลังจากที่เล่นแหล่งเสียงแรกเริ่ม โดยเวลาจะอยู่ในรูปแบบการดำเนินไปทางดนตรี",
    "EFabricNoteStyle.Straight.DisplayName": "ตรง",
    "Device_ModularEchoEffect_C.StyleIn.DisplayName": "สไตล์ขาเข้า",
    "1376C3A4460820B003090DA1E880C177": "จังหวะการซิงค์",
    "0E806B694095BE0D054E41A1DD99FECD": "สไตล์ในการให้จังหวะ",
    "Device_ModularEchoEffect_C.OnDisabled.Description": "กระตุ้นให้เกิดเหตุการณ์ เมื่อมีการปิดใช้งานอุปกรณ์",
    "Device_ModularEchoEffect_C.OnEnabled.Description": "กระตุ้นให้เกิดเหตุการณ์ เมื่อมีการเปิดใช้งานอุปกรณ์",
    "EFabricNoteStyle.Triplet.DisplayName": "สามพยางค์"
  }
}