{
  "": {
    "C4CC6BFD4C56108C84EAFCB69F6CDA2E": "Un visualizador que usa sistemas HMX.",
    "31D43A2B4A4BB147471D879330BE150C": "Pantalla del reproductor de video rota",
    "E72F759D41F8422087A8348725FBCC45": "Pantalla del reproductor de video rota",
    "036732684FA39608B9E341A22C7A7C52": "Pantalla del reproductor de video recortable",
    "8D8818A740CCDB899B8DABA3FDFF2561": "Pantalla del reproductor de video recortable",
    "8DF109B44B2C4BC82DFF45988D87FA1A": "Pantalla del reproductor de video curva",
    "AD69C0BD49AA1FF7D77D0FA07D20307B": "Pantalla del reproductor de video curva",
    "7EC903424C8552C2DE23569DE9D008AD": "Deshabilitar",
    "B15979DE4B77078487E465BB85A1AFCE": "Deshabilita esta pantalla al recibir en este canal.",
    "50DF626143B2D78E90505AAED86AB8AA": "Habilitar",
    "1C0D24CE49E785EF2DCCEB8016E7D1C4": "Habilita esta pantalla al recibir en este canal.",
    "7D5D4E814A3BCB025EF09FA9D0375185": "Pantalla del reproductor de video plana",
    "823F12F3410ECEB77D96209B84ED0890": "Pantalla del reproductor de video plana",
    "5FA3D73B468838F5C56611ADD8E969FE": "Pantalla del reproductor de video de cubo flotante",
    "AE6223A04E48CC21E8E6EBACBECB8CE8": "Pantalla del reproductor de video de cubo flotante",
    "AEFB757C4A005CD6F462FBB7C0FA545C": "Visualizador de Hmx",
    "8B8316D44909576AC40518B2765E9EAF": "Pantalla del reproductor de video de holograma",
    "E8ACCA51416B9956ABDA1EA10CDCF87B": "Pantalla del reproductor de video de holograma",
    "948B80F34E7FE8C07710AC948AE484AA": "Pantalla del reproductor de video de barras horizontales",
    "FCF7BC8048681499B9E9CFAC1D7FF53B": "Pantalla del reproductor de video de barras horizontales",
    "915597C54522E40D5BD0F4ABD7998005": "Muestra el video del dispositivo de reproductor de video activo.",
    "3C5BAEC04AD606748BC937A66A0AA94D": "Pantalla del reproductor de video de paneles",
    "8C9606E547E5C602844D2DA81A1BF3E8": "Pantalla del reproductor de video de paneles",
    "062723D24CC67B4DD68526A231462C6F": "Pantalla del reproductor de video de cubo menguante",
    "14CFB8054AC08C74F98AEFBCE45AB7A5": "Pantalla del reproductor de video de cubo menguante",
    "05DF964941DDCDF8402F9A83147CFCFD": "Pantalla del reproductor de video estándar",
    "1B78BEFC4F7D07FE048E9EB834C693F1": "Pantalla del reproductor de video estándar",
    "09D23C7548FB2E71A1F6BAB8D3391CE3": "Pantalla del reproductor de video de barras verticales",
    "56DB07A94A14119CA56BD6AFFCC17332": "Pantalla del reproductor de video de barras verticales",
    "9375B016437CA0338EE671974C87E4E1": "Pantalla del reproductor de video",
    "C2C64BE64207142CAE4DE9877936CCDA": "Galería de pantallas para reproducir videos",
    "5C50EC3F4B0C59DA9169E8B4B24A17D4": "{0} %"
  },
  "Fort.Actor.Building.Defaults": {
    "OptionDefinitionContainer.LabelOverride": "Etiqueta"
  },
  "UserOptionDefinition": {
    "B_Screen_Holo_C.Color.DisplayName": "Color",
    "B_Screen_Croppable_C.CropHeight.DisplayName": "Recortar alto",
    "B_Screen_Croppable_C.CropWidth.DisplayName": "Recortar ancho",
    "B_Screen_Billboard_C.bHasCollision.Description": "Determina si la pantalla tendrá colisión.",
    "B_Screen_Croppable_C.bHasCollision.Description": "Determina si la pantalla tendrá colisión.",
    "B_Screen_CubeFlyIn_C.bHasCollision.Description": "Determina si la pantalla tendrá colisión.",
    "B_Screen_CubeResize_C.bHasCollision.Description": "Determina si la pantalla tendrá colisión.",
    "B_Screen_Holo_C.bHasCollision.Description": "Determina si la pantalla tendrá colisión.",
    "B_VideoScreen_Parent_C.bHasCollision.Description": "Determina si la pantalla tendrá colisión.",
    "B_Screen_Billboard_C.bFollowsViewer.Description": "Determina si la pantalla rotará para orientarse al jugador.",
    "B_Screen_Croppable_C.bFollowsViewer.Description": "Determina si la pantalla rotará para orientarse al jugador.",
    "B_Screen_CubeFlyIn_C.bFollowsViewer.Description": "Determina si el video rotará para orientarse al jugador.",
    "B_Screen_CubeResize_C.bFollowsViewer.Description": "Determina si el video rotará para orientarse al jugador.",
    "B_Screen_Billboard_C.Disable.DisplayName": "Deshabilitar",
    "B_Screen_Croppable_C.Disable.DisplayName": "Deshabilitar",
    "B_Screen_CubeFlyIn_C.Disable.DisplayName": "Deshabilitar",
    "B_Screen_CubeResize_C.Disable.DisplayName": "Deshabilitar",
    "B_Screen_Holo_C.Disable.DisplayName": "Deshabilitar",
    "B_VideoScreen_Parent_C.Disable.DisplayName": "Deshabilitar",
    "B_Screen_Billboard_C.Disable.Description": "Deshabilita al recibir en este canal.",
    "B_Screen_Croppable_C.Disable.Description": "Deshabilita al recibir en este canal.",
    "B_Screen_CubeFlyIn_C.Disable.Description": "Deshabilita al recibir en este canal.",
    "B_Screen_CubeResize_C.Disable.Description": "Deshabilita al recibir en este canal.",
    "B_Screen_Holo_C.Disable.Description": "Deshabilita al recibir en este canal.",
    "B_VideoScreen_Parent_C.Disable.Description": "Deshabilita al recibir en este canal.",
    "B_Screen_Billboard_C.Enable.DisplayName": "Habilitar",
    "B_Screen_Croppable_C.Enable.DisplayName": "Habilitar",
    "B_Screen_CubeFlyIn_C.Enable.DisplayName": "Habilitar",
    "B_Screen_CubeResize_C.Enable.DisplayName": "Habilitar",
    "B_Screen_Holo_C.Enable.DisplayName": "Habilitar",
    "B_VideoScreen_Parent_C.Enable.DisplayName": "Habilitar",
    "B_Screen_Billboard_C.Enable.Description": "Habilita al recibir en este canal.",
    "B_Screen_Croppable_C.Enable.Description": "Habilita al recibir en este canal.",
    "B_Screen_CubeFlyIn_C.Enable.Description": "Habilita al recibir en este canal.",
    "B_Screen_CubeResize_C.Enable.Description": "Habilita al recibir en este canal.",
    "B_Screen_Holo_C.Enable.Description": "Habilita al recibir en este canal.",
    "B_VideoScreen_Parent_C.Enable.Description": "Habilita al recibir en este canal.",
    "B_Screen_Billboard_C.bEnabledAtStart.DisplayName": "Habilitado al inicio",
    "B_Screen_Croppable_C.bEnabledAtStart.DisplayName": "Habilitado al inicio",
    "B_Screen_CubeFlyIn_C.bEnabledAtStart.DisplayName": "Habilitado al inicio",
    "B_Screen_CubeResize_C.bEnabledAtStart.DisplayName": "Habilitado al inicio",
    "B_Screen_Holo_C.bEnabledAtStart.DisplayName": "Habilitado al inicio",
    "B_VideoScreen_Parent_C.bEnabledAtStart.DisplayName": "Habilitado al inicio",
    "B_Screen_Billboard_C.bFollowsViewer.DisplayName": "Sigue al espectador",
    "B_Screen_Croppable_C.bFollowsViewer.DisplayName": "Sigue al espectador",
    "B_Screen_CubeFlyIn_C.bFollowsViewer.DisplayName": "Sigue al espectador",
    "B_Screen_CubeResize_C.bFollowsViewer.DisplayName": "Sigue al espectador",
    "B_Screen_Billboard_C.bHasCollision.DisplayName": "Tiene colisión",
    "B_Screen_Croppable_C.bHasCollision.DisplayName": "Tiene colisión",
    "B_Screen_CubeFlyIn_C.bHasCollision.DisplayName": "Tiene colisión",
    "B_Screen_CubeResize_C.bHasCollision.DisplayName": "Tiene colisión",
    "B_Screen_Holo_C.bHasCollision.DisplayName": "Tiene colisión",
    "B_VideoScreen_Parent_C.bHasCollision.DisplayName": "Tiene colisión",
    "BoolMetaData.FalseDisplayName": "No",
    "B_Screen_Croppable_C.OffsetHorizontal.DisplayName": "Desplazamiento horizontal",
    "B_Screen_Croppable_C.OffsetVertical.DisplayName": "Desplazamiento vertical",
    "BoolMetaData.TrueDisplayName": "Sí",
    "B_Screen_Holo_C.Opacity.DisplayName": "Opacidad",
    "B_Screen_Holo_C.Opacity.Description": "Establece la opacidad de la pantalla.",
    "B_Screen_Croppable_C.OffsetHorizontal.Description": "Establece la cantidad de desplazamiento horizontal del video cuando se reduce la pantalla.",
    "B_Screen_Croppable_C.OffsetVertical.Description": "Establece la cantidad de desplazamiento vertical del video cuando se reduce la pantalla.",
    "B_Screen_Holo_C.Color.Description": "Establece el tono de color de la pantalla.",
    "B_Screen_Croppable_C.CropHeight.Description": "Establece el porcentaje de altura de la pantalla que es visible.",
    "B_Screen_Croppable_C.CropWidth.Description": "Establece el porcentaje del ancho de la pantalla que es visible.",
    "B_Screen_Billboard_C.bEnabledAtStart.Description": "Al habilitarse, la pantalla mostrará el video del dispositivo de reproductor de video activo.",
    "B_Screen_Croppable_C.bEnabledAtStart.Description": "Al habilitarse, la pantalla mostrará el video del dispositivo de reproductor de video activo.",
    "B_Screen_CubeFlyIn_C.bEnabledAtStart.Description": "Al habilitarse, la pantalla mostrará el video del dispositivo de reproductor de video activo.",
    "B_Screen_CubeResize_C.bEnabledAtStart.Description": "Al habilitarse, la pantalla mostrará el video del dispositivo de reproductor de video activo.",
    "B_Screen_Holo_C.bEnabledAtStart.Description": "Al habilitarse, la pantalla mostrará el video del dispositivo de reproductor de video activo.",
    "B_VideoScreen_Parent_C.bEnabledAtStart.Description": "Al habilitarse, la pantalla mostrará el video del dispositivo de reproductor de video activo."
  }
}