{
  "": {
    "F612323246D1D0C649BD17AFA7C72509": "Déclencher le mix si reçu depuis",
    "25896C8B42F80587FA506E80FDB0B1BB": "Active le mix à la réception d'un signal sur le canal sélectionné.",
    "5D1F0DBD499380FF2015FB9C96EA6746": "Ajoute le joueur qui déclenche en tant que point d'origine du son du haut-parleur à l'activation.",
    "8BF64B3F4C22DB964949CA8B31F51C09": "Ambiance",
    "2E57921B4E219DDB7AD61AB40F587E68": "Mixeur de sons",
    "651A8DA742CF2AA193FF22B8A15FED33": "Mixeur de sons",
    "22B4B7B941B0D5D95F5C18AAA679BF4E": "Contrôle le mix des sons.",
    "2DA9D8F04FC97A628016CA9E70A8584E": "Contrôle le mix des sons.",
    "A27F9D0443DC8EFC3D78E0AD4250FAF4": "Contrôle le mix des sons.",
    "AF6CC3C247C185EC66C85DAD01C98A02": "Créatures",
    "748F386D4482655441EB52AE16550087": "Arrêter le mix si reçu depuis",
    "611DDFF44C3A30B4FDA63E87ACADE529": "Désactive le mix à la réception d'un signal sur le canal sélectionné.",
    "C0ECC60148F6C0DE2D5246A21FC8D364": "Explosions",
    "DA47F3A64F9C5E876C1557A69FCF5222": "Pas",
    "B7B259A0416B6EC1C3F15A90FFBA1FF1": "Gadgets",
    "703C95514D2A642B1B9A0E808554759B": "Impacts",
    "30F460BB42D6BBA64EB5448C236058C1": "Musique",
    "96E465BE4C446F1C7AEA36853F40288A": "Aucun",
    "63B3B13C4640A049BDED1882D8795BF0": "Enregistrer le joueur si reçu depuis",
    "0BFD1636467269BC67075EA2F9E637E5": "Retire tous les joueurs qui déclenchent en tant que point d'origine du son du haut-parleur à l'activation.",
    "B21402814646A4120B47B3BD344D0F0C": "Retire le joueur qui déclenche en tant que point d'origine du son du haut-parleur à l'activation.",
    "2ED2F2CF40A76B3DADCE6F92281E29E7": "Effet sonore",
    "5C5B353743C55C431762DBBFE52AD69F": "Désenregistrer tous les joueurs si reçu depuis",
    "19FDE7F24BE3C637D16E9BBF97F0C5D9": "Désenregistrer le joueur si reçu depuis",
    "A6E58D374E400DADE8BC8EB6114A987B": "Moteurs de véhicules",
    "378561844031B225522285B7CD01F56F": "Véhicules",
    "53C7B5B54C487395EA88FA960767CC45": "Armes"
  },
  "Fort.Actor.Building.Defaults": {
    "OptionDefinitionContainer.LabelOverride": "Étiquette"
  },
  "UserOptionDefinition": {
    "Device_CRD_AudioMixer_C.Activate Mix.DisplayName": "Activer le mix",
    "Device_CRD_AudioMixer_C.bActivateInEditMode.DisplayName": "Activer en mode modification",
    "Device_CRD_AudioMixer_C.bActivateOnGameStart.DisplayName": "Déclencher au démarrage du jeu",
    "Device_CRD_AudioMixer_C.Activate Mix.Description": "Active le mix associé à ce mixeur.",
    "Device_CRD_AudioMixer_C.Bus.DisplayName": "Bus",
    "Device_CRD_AudioMixer_C.CanBeHeardBy.DisplayName": "Peut être entendu par",
    "Device_CRD_AudioMixer_C.Deactivate Mix.DisplayName": "Désactiver le mix",
    "Device_CRD_AudioMixer_C.Deactivate Mix.Description": "Désactive le mix associé à ce mixeur.",
    "ECreativeRegisteredPlayerGroups.Everyone.DisplayName": "Tout le monde",
    "Device_CRD_AudioMixer_C.FaderValue.DisplayName": "Valeur du fondu",
    "Device_CRD_AudioMixer_C.Mix.DisplayName": "Mix",
    "ECreativeRegisteredPlayerGroups.NonRegisteredPlayers.DisplayName": "Joueurs non enregistrés",
    "ECreativeRegisteredPlayerGroups.None.DisplayName": "Personne",
    "BoolMetaData.FalseDisplayName": "Non",
    "BoolMetaData.TrueDisplayName": "Oui",
    "Device_CRD_AudioMixer_C.Register Player.DisplayName": "Enregistrer le joueur",
    "ECreativeRegisteredPlayerGroups.RegisteredPlayers.DisplayName": "Joueurs enregistrés",
    "Device_CRD_AudioMixer_C.Register Player.Description": "Enregistre un joueur. Utilisé en conjonction avec l'option Peut être entendu par.",
    "Device_CRD_AudioMixer_C.Mix.Description": "Définit le mix activé ou désactivé par cet appareil.",
    "Device_CRD_AudioMixer_C.CanBeHeardBy.Description": "Définit les joueurs qui profitent du mix.",
    "Device_CRD_AudioMixer_C.Unregister All Players.DisplayName": "Désenregistrer tous les joueurs",
    "Device_CRD_AudioMixer_C.Unregister Player.DisplayName": "Désenregistrer le joueur",
    "Device_CRD_AudioMixer_C.Unregister Player.Description": "Désenregistre un joueur enregistré. Utilisé en conjonction avec l'option Peut être entendu par.",
    "Device_CRD_AudioMixer_C.Unregister All Players.Description": "Désenregistre tous les joueurs enregistrés. Utilisé en conjonction avec l'option Peut être entendu par.",
    "Device_CRD_AudioMixer_C.FaderValue.Description": "Tant qu'un mix n'est pas défini, ceci est la valeur sur laquelle le bus ci-dessus sera défini.",
    "Device_CRD_AudioMixer_C.Bus.Description": "Tant qu'un mix n'est pas défini, un bus sera assigné à la place.",
    "Device_CRD_AudioMixer_C.bActivateInEditMode.Description": "Si activé, le mix se déclenche automatiquement en mode modification.",
    "Device_CRD_AudioMixer_C.bActivateOnGameStart.Description": "Si activé, le mix se déclenche automatiquement au démarrage du jeu."
  }
}